Metadata-Version: 1.0
Name: akki-distributions
Version: 0.1
Summary: Gaussian and Binomial distributions
Home-page: UNKNOWN
Author: Akshay Jaitly
Author-email: UNKNOWN
License: UNKNOWN
Platform: UNKNOWN
